setup.py
src/fakebook/__init__.py
src/fakebook/fakebook.py
src/fakebook.egg-info/PKG-INFO
src/fakebook.egg-info/SOURCES.txt
src/fakebook.egg-info/dependency_links.txt
src/fakebook.egg-info/requires.txt
src/fakebook.egg-info/top_level.txt