Metadata-Version: 1.0
Name: fakebook
Version: 0.1
Summary: Tool for managing facebook test users
Home-page: https://github.com/lolek09/fakebook
Author: Karol Majta
Author-email: karol@karolmajta.com
License: JSON License
Keywords: facebook test users
Platform: UNKNOWN
